{
  "homeserver": "http://127.0.0.1:8008",
  "server_name": "jgaga.tk",
  "bot_user_id": "@bot:jgaga.tk",
  "token_path": "/root/data/docker_data/_secrets/matrix-bot/access_token",
  "city": "中国江苏省徐州市",
  "latitude": 34.2044,
  "longitude": 117.2841,
  "timezone": "Asia/Shanghai",
  "target_users": [
    "@honey:jgaga.tk",
    "@black:jgaga.tk",
    "@admin2:jgaga.tk",
    "@admin:jgaga.tk"
  ],
  "target_rooms": [],
  "send_to_joined_rooms": false,
  "state_path": "/root/data/docker_data/synapse/scripts/matrix-bot-weather.state.json",
  "default_weather_time": "05:00",
  "schedule_grace_minutes": 15,
  "sync_state_path": "/root/data/docker_data/synapse/scripts/matrix-bot-sync.state.json",
  "weather_users": {
    "@honey:jgaga.tk": {
      "enabled": true,
      "time": "05:00"
    },
    "@black:jgaga.tk": {
      "enabled": true,
      "time": "05:00"
    },
    "@admin2:jgaga.tk": {
      "enabled": true,
      "time": "05:00"
    },
    "@admin:jgaga.tk": {
      "enabled": true,
      "time": "05:00"
    }
  },
  "direct_rooms": {
    "@admin2:jgaga.tk": "!XhGkzbjFkeeBASkhVR:jgaga.tk",
    "@admin:jgaga.tk": "!drXtPnaMTzQGAbxirK:jgaga.tk",
    "@black:jgaga.tk": "!QpMcdNGzPRsdbgDynk:jgaga.tk",
    "@honey:jgaga.tk": "!KvyLbnBxPBQMJcBOMo:jgaga.tk"
  }
}
